{
    "version": "6.4.3",
    "description": "A prompt theme engine for any shell",
    "homepage": "https://ohmyposh.dev",
    "license": {
        "identifier": "GPL-3.0-only",
        "url": "https://github.com/JanDeDobbeleer/oh-my-posh/blob/main/COPYING"
    },
    "architecture": {
        "64bit": {
            "url": "https://github.com/JanDeDobbeleer/oh-my-posh3/releases/download/v6.4.3/posh-windows-wsl-amd64.7z",
            "hash": "85e890d593c3058b640ddf25b656931283cc7882fb4086e80a5e55ec2890bc1f"
        }
    },
    "bin": "oh-my-posh.exe",
    "checkver": {
        "github": "https://github.com/JanDeDobbeleer/oh-my-posh"
    },
    "autoupdate": {
        "architecture": {
            "64bit": {
                "url": "https://github.com/JanDeDobbeleer/oh-my-posh3/releases/download/v$version/posh-windows-wsl-amd64.7z"
            }
        },
        "hash": {
            "url": "$url.sha256",
            "regex": "$sha256"
        }
    }
}
